skosify/__init__.py
skosify/check.py
skosify/cli.py
skosify/config.py
skosify/infer.py
skosify/skosify.py
skosify/rdftools/__init__.py
skosify/rdftools/access.py
skosify/rdftools/io.py
skosify/rdftools/modify.py
skosify/rdftools/namespace.py
skosify-2.3.0.dist-info/LICENSE
skosify-2.3.0.dist-info/METADATA
skosify-2.3.0.dist-info/WHEEL
skosify-2.3.0.dist-info/entry_points.txt
skosify-2.3.0.dist-info/top_level.txt
skosify-2.3.0.dist-info/RECORD
