Metadata-Version: 2.1
Name: skosify
Version: 2.3.0
Summary: SKOS converter for RDFS/OWL/SKOS vocabularies.
Home-page: https://github.com/NatLibFi/Skosify
Author: Osma Suominen
Author-email: osma.suominen@helsinki.fi
License: MIT
Keywords: rdf skos
Platform: UNKNOWN
Classifier: Programming Language :: Python
Classifier: Programming Language :: Python :: 3.6
Classifier: Programming Language :: Python :: 3.7
Classifier: Programming Language :: Python :: 3.8
Classifier: Programming Language :: Python :: 3.9
Requires-Dist: rdflib
